chinese_holidays/__init__.py
chinese_holidays/server.py
chinese_holidays-0.1.10.dist-info/METADATA
chinese_holidays-0.1.10.dist-info/WHEEL
chinese_holidays-0.1.10.dist-info/entry_points.txt
chinese_holidays-0.1.10.dist-info/licenses/LICENSE
chinese_holidays-0.1.10.dist-info/RECORD
