Metadata-Version: 2.4
Name: chinese-holidays
Version: 0.1.10
Summary: Query information about Chinese holidays
Author-email: OSpoon <zxin088@gmail.com>
License-File: LICENSE
Requires-Python: >=3.10
Requires-Dist: httpx>=0.28.1
Requires-Dist: mcp>=1.2.0
